textworld_express/__init__.py
textworld_express/constants.py
textworld_express/cooking_world.json
textworld_express/textworld-express.jar
textworld_express/textworld_express.py
textworld_express/twc_objects.folds.json
textworld_express/version.py
textworld_express-1.0.5.dist-info/LICENSE
textworld_express-1.0.5.dist-info/METADATA
textworld_express-1.0.5.dist-info/WHEEL
textworld_express-1.0.5.dist-info/top_level.txt
textworld_express-1.0.5.dist-info/RECORD
