Metadata-Version: 2.1
Name: textworld_express
Version: 1.0.5
Summary: TextWorldExpress: a highly optimized reimplementation of three text game benchmarks focusing on instruction following, commonsense reasoning, and object identification.
Home-page: https://github.com/cognitiveailab/TextWorldExpress
Author: Peter Jansen
License-File: LICENSE
Requires-Dist: py4j
Requires-Dist: orjson
Requires-Dist: prompt-toolkit
Provides-Extra: webserver
Requires-Dist: py4j; extra == "webserver"
Requires-Dist: orjson; extra == "webserver"
Requires-Dist: prompt-toolkit; extra == "webserver"
Requires-Dist: pywebio; extra == "webserver"
